Workbook

Sheet Inputs
A1: ScrollJar money model
A2: How to use: change the yellow cells in column E (Your guess). Blue numbers are assumptions; everything on the Results tab recalculates. All money in US dollars, per year, about 2 years after launch.
A4: Input | B4: Hard | C4: Middle | D4: Good | E4: Your guess | F4: Where the number comes from
A5: People using the free app | B5: 2000 | C5: 20000 | D5: 100000 | E5: 20000 | F5: Illustrative guess, not a forecast.
A6: Share of free users who buy Plus | B6: 0.02 | C6: 0.03 | D6: 0.04 | E6: 0.03 | F6: Rough rule of thumb for subscription apps (2–5%); not researched for this market.
A7: Plus price per year | B7: 29.99 | C7: 29.99 | D7: 29.99 | E7: 29.99 | F7: Proposed price (sketchpad, 2026-10-14).
A8: Families on the Family plan | B8: 10 | C8: 100 | D8: 800 | E8: 100 | F8: Illustrative guess.
A9: Family price per year | B9: 49.99 | C9: 49.99 | D9: 49.99 | E9: 49.99 | F9: Proposed price (sketchpad, 2026-10-14).
A10: Apple's cut on app subscriptions | B10: 0.15 | C10: 0.15 | D10: 0.15 | E10: 0.15 | F10: Apple Small Business Program rate (under $1M a year).
A11: Paying companies (Teams) | B11: 0 | C11: 3 | D11: 15 | E11: 3 | F11: Illustrative guess.
A12: Average employees per company | B12: 100 | C12: 100 | D12: 150 | E12: 100 | F12: Illustrative guess.
A13: Price per employee per month | B13: 4 | C13: 4 | D13: 4 | E13: 4 | F13: Teams draft price (scrolljar-teams-spec.md).
A14: Card fee on company invoices | B14: 0.03 | C14: 0.03 | D14: 0.03 | E14: 0.03 | F14: Approximate card processing fee; bank transfer would be lower.
A15: Running costs per year | B15: 5000 | C15: 8000 | D15: 20000 | E15: 8000 | F15: Servers, Apple developer account, domain, email, accountant, US company. Rough estimate.
A16: One-off cost to build the app | B16: 1500 | C16: 1500 | D16: 1500 | E16: 1500 | F16: Used Mac + iPhone if you build it yourself. A freelance iOS developer would be roughly $20,000–60,000.
A17: Salary you want to pay yourself, per month | B17: 2200 | C17: 2200 | D17: 2200 | E17: 2200 | F17: About €2,000 at roughly $1.10 per euro.

Sheet Results
A1: Results
A2: Every number here is a formula fed by the Inputs tab. Charity money passes through ScrollJar and never counts as income.
A4: Per year | B4: Hard | C4: Middle | D4: Good | E4: Your guess
A5: Plus payers | B5: =Inputs!B$5*Inputs!B$6 -> 40 | C5: =Inputs!C$5*Inputs!C$6 -> 600 | D5: =Inputs!D$5*Inputs!D$6 -> 4000 | E5: =Inputs!E$5*Inputs!E$6 -> 600
A6: Income from Plus | B6: =B5*Inputs!B$7*(1-Inputs!B$10) -> 1019.66 | C6: =C5*Inputs!C$7*(1-Inputs!C$10) -> 15294.9 | D6: =D5*Inputs!D$7*(1-Inputs!D$10) -> 101966 | E6: =E5*Inputs!E$7*(1-Inputs!E$10) -> 15294.9
A7: Income from Families | B7: =Inputs!B$8*Inputs!B$9*(1-Inputs!B$10) -> 424.915 | C7: =Inputs!C$8*Inputs!C$9*(1-Inputs!C$10) -> 4249.15 | D7: =Inputs!D$8*Inputs!D$9*(1-Inputs!D$10) -> 33993.2 | E7: =Inputs!E$8*Inputs!E$9*(1-Inputs!E$10) -> 4249.15
A8: Income from companies | B8: =Inputs!B$11*Inputs!B$12*Inputs!B$13*12*(1-Inputs!B$14) -> 0 | C8: =Inputs!C$11*Inputs!C$12*Inputs!C$13*12*(1-Inputs!C$14) -> 13968 | D8: =Inputs!D$11*Inputs!D$12*Inputs!D$13*12*(1-Inputs!D$14) -> 104760 | E8: =Inputs!E$11*Inputs!E$12*Inputs!E$13*12*(1-Inputs!E$14) -> 13968
A9: Total income | B9: =SUM(B6:B8) -> 1444.575 | C9: =SUM(C6:C8) -> 33512.05 | D9: =SUM(D6:D8) -> 240719.2 | E9: =SUM(E6:E8) -> 33512.05
A10: Running costs | B10: =Inputs!B$15 -> 5000 | C10: =Inputs!C$15 -> 8000 | D10: =Inputs!D$15 -> 20000 | E10: =Inputs!E$15 -> 8000
A11: Profit before paying yourself | B11: =B9-B10 -> -3555.425 | C11: =C9-C10 -> 25512.05 | D11: =D9-D10 -> 220719.2 | E11: =E9-E10 -> 25512.05
A12: Salary it could pay you, per month | B12: =MAX(0,B11)/12 -> 0 | C12: =MAX(0,C11)/12 -> 2126.0042 | D12: =MAX(0,D11)/12 -> 18393.267 | E12: =MAX(0,E11)/12 -> 2126.0042
A13: Months to earn back the build cost | B13: =IF(B11>0,Inputs!B$16/(B11/12),"never") -> never | C13: =IF(C11>0,Inputs!C$16/(C11/12),"never") -> 0.70554895 | D13: =IF(D11>0,Inputs!D$16/(D11/12),"never") -> 0.081551582 | E13: =IF(E11>0,Inputs!E$16/(E11/12),"never") -> 0.70554895
A15: To pay yourself your target salary, you need ONE of:
A16: …this many Plus payers | B16: =(Inputs!B$17*12+Inputs!B$15)/(Inputs!B$7*(1-Inputs!B$10)) -> 1231.7831 | C16: =(Inputs!C$17*12+Inputs!C$15)/(Inputs!C$7*(1-Inputs!C$10)) -> 1349.4694 | D16: =(Inputs!D$17*12+Inputs!D$15)/(Inputs!D$7*(1-Inputs!D$10)) -> 1820.2146 | E16: =(Inputs!E$17*12+Inputs!E$15)/(Inputs!E$7*(1-Inputs!E$10)) -> 1349.4694
A17: …or this many families | B17: =(Inputs!B$17*12+Inputs!B$15)/(Inputs!B$9*(1-Inputs!B$10)) -> 738.97132 | C17: =(Inputs!C$17*12+Inputs!C$15)/(Inputs!C$9*(1-Inputs!C$10)) -> 809.57368 | D17: =(Inputs!D$17*12+Inputs!D$15)/(Inputs!D$9*(1-Inputs!D$10)) -> 1091.9831 | E17: =(Inputs!E$17*12+Inputs!E$15)/(Inputs!E$9*(1-Inputs!E$10)) -> 809.57368
A18: …or this many companies (at the average size) | B18: =IFERROR((Inputs!B$17*12+Inputs!B$15)/(Inputs!B$12*Inputs!B$13*12*(1-Inputs!B$14)),0) -> 6.7439863 | C18: =IFERROR((Inputs!C$17*12+Inputs!C$15)/(Inputs!C$12*Inputs!C$13*12*(1-Inputs!C$14)),0) -> 7.3883162 | D18: =IFERROR((Inputs!D$17*12+Inputs!D$15)/(Inputs!D$12*Inputs!D$13*12*(1-Inputs!D$14)),0) -> 6.6437572 | E18: =IFERROR((Inputs!E$17*12+Inputs!E$15)/(Inputs!E$12*Inputs!E$13*12*(1-Inputs!E$14)),0) -> 7.3883162
A20: Green = pulled straight from the Inputs tab. Black = calculated here. 'never' means the plan loses money in that scenario.
